tishinaUtils/__init__.py
tishinaUtils/tishinaUtils.py
tishinaUtils-0.0.4.dist-info/LICENSE
tishinaUtils-0.0.4.dist-info/METADATA
tishinaUtils-0.0.4.dist-info/WHEEL
tishinaUtils-0.0.4.dist-info/top_level.txt
tishinaUtils-0.0.4.dist-info/RECORD
